tests/__init__.py
tests/conftest.py
tests/debug.py
uun_iot/Gateway.py
uun_iot/UuAppClient.py
uun_iot/__init__.py
uun_iot/diagnostic.py
uun_iot/exceptions.py
uun_iot/py.typed
uun_iot/typing.py
uun_iot/utils.py
uun_iot/events/EvConfUpdate.py
uun_iot/events/EvExternal.py
uun_iot/events/EvStart.py
uun_iot/events/EvStop.py
uun_iot/events/EvTick.py
uun_iot/events/Event.py
uun_iot/events/__init__.py
uun_iot/modules/BaseHealthCheck.py
uun_iot/modules/ConfigUpdater.py
uun_iot/modules/Heartbeat.py
uun_iot/modules/Module.py
uun_iot/modules/SocketServer.py
uun_iot/modules/__init__.py
uun_iot-0.12.14.dist-info/licenses/LICENSE.md
uun_iot-0.12.14.dist-info/METADATA
uun_iot-0.12.14.dist-info/WHEEL
uun_iot-0.12.14.dist-info/top_level.txt
uun_iot-0.12.14.dist-info/RECORD
