Metadata-Version: 2.4
Name: uun-iot
Version: 0.12.14
Summary: Modular framework for communication with UuApp and utility functionality
Home-page: https://uuapp.plus4u.net/uu-bookkit-maing01/38c7532545984b3797c5719390b523a8/book/page?code=71150832
Author: (UUN) Tomáš Faikl
Author-email: tomas.faikl@unicornuniversity.net
Classifier: Programming Language :: Python :: 3
Classifier: License :: OSI Approved :: MIT License
Requires-Python: >=3.7
License-File: LICENSE.md
Requires-Dist: requests>=2.24.0
Requires-Dist: requests_toolbelt>=0.9.1
Dynamic: author
Dynamic: author-email
Dynamic: classifier
Dynamic: description
Dynamic: description-content-type
Dynamic: home-page
Dynamic: license-file
Dynamic: requires-dist
Dynamic: requires-python
Dynamic: summary
